aadt/__init__.py
aadt/builder.py
aadt/cli.py
aadt/config.py
aadt/git.py
aadt/init.py
aadt/manifest.py
aadt/run.py
aadt/schema.json
aadt/templates/ANKI.md
aadt/templates/CLAUDE.md
aadt/templates/README.md.template
aadt/templates/__init__.py
aadt/templates/ankidoc/ANKI_API.md
aadt/templates/ankidoc/ANKI_CORE.md
aadt/templates/ankidoc/ANKI_PATTERNS.md
aadt/templates/ankidoc/ANKI_TROUBLESHOOTING.md
aadt/templates/ankidoc/examples/advanced_features.py
aadt/templates/ankidoc/examples/basic_operations.py
aadt/templates/ankidoc/examples/ui_development.py
aadt/templates/gitignore
aadt/templates/pyproject.toml.template
aadt/templates/python-version
aadt/ui.py
aadt/utils.py
aadt-1.7.0.dist-info/WHEEL
aadt-1.7.0.dist-info/entry_points.txt
aadt-1.7.0.dist-info/METADATA
aadt-1.7.0.dist-info/RECORD
