Metadata-Version: 2.3
Name: aadt
Version: 1.7.0
Summary: Anki Addon Dev ToolKit
Keywords: anki,development,build-tools
Author: Libukai
License: AGPL-3.0-or-later
Classifier: Development Status :: 3 - Alpha
Classifier: Intended Audience :: Developers
Classifier: Topic :: Software Development :: Build Tools
Classifier: License :: OSI Approved :: GNU Affero General Public License v3
Classifier: Programming Language :: Python :: 3.13
Classifier: Operating System :: POSIX
Classifier: Operating System :: MacOS
Requires-Dist: jsonschema>=4.4.0
Requires-Dist: whichcraft>=0.6.1
Requires-Dist: questionary>=2.1.0
Requires-Python: >=3.13
Project-URL: Homepage, https://github.com/libukai/Anki-Addon-Dev-ToolKit
Project-URL: Repository, https://github.com/libukai/Anki-Addon-Dev-ToolKit
